digint/__init__.py
digint/digint.py
digint/errors.py
digint/notation_format.py
digint/tools.py
digint/typings.py
digint/userint.py
digint-1.0.3.0.dist-info/LICENCE
digint-1.0.3.0.dist-info/METADATA
digint-1.0.3.0.dist-info/WHEEL
digint-1.0.3.0.dist-info/top_level.txt
digint-1.0.3.0.dist-info/zip-safe
digint-1.0.3.0.dist-info/RECORD
