Metadata-Version: 2.1
Name: digint
Version: 1.0.3.0
Summary: A python module for manipulating positional integers across any numerical base, providing advanced digit-level control.
Author-email: Markus Hammer <107761433+MarkusHammer@users.noreply.github.com>
Project-URL: Homepage, https://github.com/MarkusHammer/digint
Project-URL: Documentation, https://MarkusHammer.github.io/digint
Project-URL: Github, https://github.com/MarkusHammer/digint
Project-URL: Issues, https://github.com/MarkusHammer/digint/issues
Project-URL: Pull Requests, https://github.com/MarkusHammer/digint/pulls
Project-URL: Git, https://github.com/MarkusHammer/digint.git
Keywords: integer,digit,digitwise,bitwise,manipulation,number,numeric,numerical,bases,positional,number systems,mathematics,binary,hexadecimal,custom,notation
Classifier: License :: OSI Approved :: Mozilla Public License 2.0 (MPL 2.0)
Classifier: Development Status :: 5 - Production/Stable
Classifier: Intended Audience :: Developers
Classifier: Intended Audience :: Science/Research
Classifier: Intended Audience :: Education
Classifier: Typing :: Typed
Classifier: Natural Language :: English
Classifier: Topic :: Scientific/Engineering :: Mathematics
Classifier: Topic :: Software Development :: Libraries :: Python Modules
Classifier: Programming Language :: Python
Classifier: Programming Language :: Python :: 3
Classifier: Programming Language :: Python :: 3.7
Classifier: Programming Language :: Python :: 3.10
Classifier: Programming Language :: Python :: 3.11
Classifier: Programming Language :: Python :: 3.12
Requires-Python: >=3.7
License-File: LICENCE
Requires-Dist: typing-extensions ; python_version <= "3.10"
Provides-Extra: dev
Requires-Dist: setuptools >=64.0.0 ; extra == 'dev'
Requires-Dist: pipreqs ; extra == 'dev'
Requires-Dist: validate-pyproject[all] ; extra == 'dev'
Requires-Dist: build ; extra == 'dev'
Requires-Dist: twine ; extra == 'dev'
Requires-Dist: coverage ; extra == 'dev'
Requires-Dist: pdoc3 ; extra == 'dev'
Requires-Dist: pyright ; extra == 'dev'
Requires-Dist: pylint ; extra == 'dev'
Requires-Dist: flake8 ; extra == 'dev'
